mytqdm/__init__.py
mytqdm/mytqdm.py
mytqdm-1.0.11.dist-info/licenses/LICENSE
mytqdm-1.0.11.dist-info/METADATA
mytqdm-1.0.11.dist-info/WHEEL
mytqdm-1.0.11.dist-info/top_level.txt
mytqdm-1.0.11.dist-info/RECORD
