Metadata-Version: 2.4
Name: mytqdm
Version: 1.0.11
Summary: mytqdm is a wrapper around tqdm that allows to see and share your progress on https://mytqdm.app
Home-page: https://github.com/padmalcom/mytqdm
Author: Jonas Freiknecht
Author-email: j.freiknecht@googlemail.com
License: MIT
Project-URL: Documentation, https://mytqdm.app/docs
Project-URL: GitHub, https://github.com/padmalcom/mytqdm
Project-URL: Changelog, https://github.com/padmalcom/mytqdm/blob/master/CHANGELOG.md
Classifier: Development Status :: 4 - Beta
Classifier: Intended Audience :: Developers
Classifier: License :: OSI Approved :: MIT License
Classifier: Operating System :: OS Independent
Classifier: Programming Language :: Python :: 3.8
Classifier: Programming Language :: Python :: 3.9
Classifier: Programming Language :: Python :: 3.10
Classifier: Programming Language :: Python :: 3.11
Classifier: Programming Language :: Python :: 3.12
Classifier: Programming Language :: Python :: 3.13
Requires-Python: >=3.8
License-File: LICENSE
Requires-Dist: tqdm>=4.67.1
Dynamic: author
Dynamic: author-email
Dynamic: classifier
Dynamic: description
Dynamic: description-content-type
Dynamic: home-page
Dynamic: license
Dynamic: license-file
Dynamic: project-url
Dynamic: requires-dist
Dynamic: requires-python
Dynamic: summary
